prediction_task/__init__.py
prediction_task-0.0.1.dist-info/LICENSE.txt
prediction_task-0.0.1.dist-info/METADATA
prediction_task-0.0.1.dist-info/WHEEL
prediction_task-0.0.1.dist-info/top_level.txt
prediction_task-0.0.1.dist-info/RECORD
